pymeteofr/__init__.py
pymeteofr/services.py
pymeteofr-0.1.0.dist-info/AUTHORS.rst
pymeteofr-0.1.0.dist-info/LICENSE
pymeteofr-0.1.0.dist-info/METADATA
pymeteofr-0.1.0.dist-info/WHEEL
pymeteofr-0.1.0.dist-info/top_level.txt
pymeteofr-0.1.0.dist-info/RECORD
