Metadata-Version: 2.1
Name: pymeteofr
Version: 0.1.0
Summary: Python wrapper for the meteo-france web services.
Home-page: https://github.com/aetperf/pymeteofr
Author: Francois Pacull
Author-email: francois.pacull@architecture-performance.fr
License: MIT license
Keywords: pymeteofr
Platform: UNKNOWN
Classifier: Development Status :: 2 - Pre-Alpha
Classifier: Intended Audience :: Developers
Classifier: License :: OSI Approved :: MIT License
Classifier: Natural Language :: English
Classifier: Programming Language :: Python :: 3
Classifier: Programming Language :: Python :: 3.6
Classifier: Programming Language :: Python :: 3.7
Classifier: Programming Language :: Python :: 3.8
Requires-Python: >=3.6
Requires-Dist: requests
Requires-Dist: matplotlib
Requires-Dist: numpy
Requires-Dist: pandas
Requires-Dist: xmltodict
Requires-Dist: rasterio
Requires-Dist: scipy
Requires-Dist: xarray
Requires-Dist: imageio
Requires-Dist: colorcet
Requires-Dist: geopandas
Requires-Dist: descartes
Requires-Dist: pygifsicle
